{
  "project_info": {
    "project_number": "1044549057133",
    "project_id": "organizze-e6ab7",
    "storage_bucket": "organizze-e6ab7.appspot.com"
  },
  "client": [
    {
      "client_info": {
        "mobilesdk_app_id": "1:1044549057133:android:b9ed89496349d1cb431d64",
        "android_client_info": {
          "package_name": "com.example.organizze"
        }
      },
      "oauth_client": [
        {
          "client_id": "1044549057133-o1t1frq804j44gbts3o9c7fif9lqkcc0.apps.googleusercontent.com",
          "client_type": 3
        }
      ],
      "api_key": [
        {
          "current_key": "AIzaSyB3eENDrsOnLOv5mS5U554dPQ0pdQ8v35U"
        }
      ],
      "services": {
        "appinvite_service": {
          "other_platform_oauth_client": [
            {
              "client_id": "1044549057133-o1t1frq804j44gbts3o9c7fif9lqkcc0.apps.googleusercontent.com",
              "client_type": 3
            }
          ]
        }
      }
    }
  ],
  "configuration_version": "1"
}